[
  { "time": 3.5, "arrow_type": "right" },
    { "time": 7.0, "arrow_type": "down" },
    { "time": 9.0, "arrow_type": "up" },
    { "time": 12.0, "arrow_type": "down" },
    { "time": 14.5, "arrow_type": "up" },
    { "time": 15.5, "arrow_type": "up" },
    { "time": 20.0, "arrow_type": "down" },
    { "time": 22.5, "arrow_type": "right" },
    { "time": 25.5, "arrow_type": "down" },
    { "time": 28.0, "arrow_type": "left" },
    { "time": 30.5, "arrow_type": "down" },
    { "time": 33.5, "arrow_type": "up" },
    { "time": 37.0, "arrow_type": "down" },
    { "time": 38.5, "arrow_type": "down" },
    { "time": 43.5, "arrow_type": "left" },
    { "time": 46.0, "arrow_type": "left" },
    { "time": 49.0, "arrow_type": "up" },
    { "time": 52.0, "arrow_type": "left" },
    { "time": 55.0, "arrow_type": "right" },
    { "time": 58.0, "arrow_type": "up" },
    { "time": 60.2, "arrow_type": "down" },
    { "time": 61.5, "arrow_type": "right" },
    { "time": 63.0, "arrow_type": "up" },
    { "time": 64.5, "arrow_type": "left" },
    { "time": 67.3, "arrow_type": "right" },
    { "time": 68.8, "arrow_type": "up" },
    { "time": 70.0, "arrow_type": "down" },
    { "time": 71.2, "arrow_type": "left" },
    { "time": 72.4, "arrow_type": "right" },
    { "time": 73.6, "arrow_type": "up" },
    { "time": 74.7, "arrow_type": "down" },
    { "time": 75.9, "arrow_type": "left" },
    { "time": 77.0, "arrow_type": "right" },
    { "time": 78.2, "arrow_type": "down" },
    { "time": 79.4, "arrow_type": "up" },
    { "time": 80.6, "arrow_type": "left" },
    { "time": 81.7, "arrow_type": "right" },
    { "time": 82.8, "arrow_type": "up" },
    { "time": 83.9, "arrow_type": "down" },
    { "time": 85.0, "arrow_type": "right" },
    { "time": 86.1, "arrow_type": "left" },
    { "time": 87.2, "arrow_type": "up" },
    { "time": 88.3, "arrow_type": "down" },
    { "time": 89.4, "arrow_type": "left" },
    { "time": 90.5, "arrow_type": "up" },
  { "time": 91.6, "arrow_type": "right" },
  { "time": 92.7, "arrow_type": "down" },
  { "time": 94.9, "arrow_type": "up" },
  { "time": 96.1, "arrow_type": "right" },
  { "time": 97.3, "arrow_type": "down" },
  { "time": 98.5, "arrow_type": "left" },
  { "time": 99.7, "arrow_type": "up" },
  { "time": 101.0, "arrow_type": "down" },
  { "time": 102.3, "arrow_type": "right" },
  { "time": 103.6, "arrow_type": "up" },
  { "time": 105.0, "arrow_type": "left" },
  { "time": 106.4, "arrow_type": "down" },
  { "time": 107.9, "arrow_type": "right" },
  { "time": 109.4, "arrow_type": "up" },
  { "time": 110.9, "arrow_type": "down" },
  { "time": 112.5, "arrow_type": "left" },
  { "time": 114.1, "arrow_type": "right" },
  { "time": 115.8, "arrow_type": "up" },
  { "time": 117.5, "arrow_type": "down" },
  { "time": 119.3, "arrow_type": "left" },
  { "time": 121.1, "arrow_type": "right" },
  { "time": 124.9, "arrow_type": "down" },
  { "time": 126.9, "arrow_type": "left" },
  { "time": 128.9, "arrow_type": "right" },
  { "time": 131.0, "arrow_type": "down" },
  { "time": 133.1, "arrow_type": "up" },
  { "time": 135.3, "arrow_type": "left" },
  { "time": 137.5, "arrow_type": "right" },
  { "time": 139.8, "arrow_type": "up" },
  { "time": 142.1, "arrow_type": "down" },
  { "time": 144.5, "arrow_type": "left" },
  { "time": 146.9, "arrow_type": "right" },
  { "time": 149.4, "arrow_type": "down" },
  { "time": 151.9, "arrow_type": "up" },
  { "time": 154.5, "arrow_type": "left" },
  { "time": 157.1, "arrow_type": "right" },
  { "time": 159.8, "arrow_type": "up" },
  { "time": 162.5, "arrow_type": "down" },
  { "time": 165.3, "arrow_type": "left" },
  { "time": 168.1, "arrow_type": "right" },
  { "time": 171.0, "arrow_type": "up" },
  { "time": 173.9, "arrow_type": "down" },
  { "time": 176.9, "arrow_type": "left" },
  { "time": 179.9, "arrow_type": "right" },
  { "time": 182.8, "arrow_type": "up" },
  { "time": 185.7, "arrow_type": "down" },
  { "time": 188.5, "arrow_type": "left" },
  { "time": 191.2, "arrow_type": "right" },
  { "time": 193.8, "arrow_type": "up" },
  { "time": 196.3, "arrow_type": "left" },
  { "time": 198.7, "arrow_type": "down" },
  { "time": 201.0, "arrow_type": "right" },
  { "time": 203.2, "arrow_type": "down" },
  { "time": 205.3, "arrow_type": "up" },
  { "time": 209.2, "arrow_type": "right" },
  { "time": 211.0, "arrow_type": "down" },
  { "time": 212.7, "arrow_type": "up" },
  { "time": 214.3, "arrow_type": "left" },
  { "time": 215.8, "arrow_type": "right" },
  { "time": 217.2, "arrow_type": "down" },
  { "time": 218.5, "arrow_type": "up" },
  { "time": 219.7, "arrow_type": "left" },
  { "time": 220.8, "arrow_type": "right" },
  { "time": 221.8, "arrow_type": "down" },
  { "time": 222.7, "arrow_type": "up" },
  { "time": 223.5, "arrow_type": "left" },
  { "time": 224.2, "arrow_type": "right" },
  { "time": 224.8, "arrow_type": "up" },
  { "time": 225.3, "arrow_type": "down" },
  { "time": 225.7, "arrow_type": "left" },
  { "time": 226.0, "arrow_type": "right" },
  { "time": 226.2, "arrow_type": "up" },
  { "time": 226.3, "arrow_type": "down" },
  { "time": 227.0, "arrow_type": "left" },
  { "time": 227.8, "arrow_type": "right" },
  { "time": 228.7, "arrow_type": "up" },
  { "time": 229.7, "arrow_type": "down" },
  { "time": 230.8, "arrow_type": "left" },
  { "time": 232.0, "arrow_type": "right" },
  { "time": 233.3, "arrow_type": "up" },
  { "time": 234.7, "arrow_type": "down" },
  { "time": 236.2, "arrow_type": "left" },
  { "time": 237.8, "arrow_type": "right" }
]